[
    {
        "added_on": 1777908355,
        "amount_left": 0,
        "auto_tmm": true,
        "availability": -1,
        "category": "",
        "comment": "",
        "completed": 13728288749,
        "completion_on": 1777908509,
        "content_path": "/Volumes/IznoServer SSD/torrents/complete/Stranger.Things.Tales.from.85.S01.MULTi.VF2.1080p.WEB.H265-SUPPLY",
        "dl_limit": 0,
        "dlspeed": 0,
        "download_path": "/Volumes/IznoServer SSD/torrents/incomplete",
        "downloaded": 13755122931,
        "downloaded_session": 0,
        "eta": 8640000,
        "f_l_piece_prio": false,
        "force_start": false,
        "has_metadata": true,
        "hash": "11984415d50696dff491afe11f329b92b13228f7",
        "inactive_seeding_time_limit": -2,
        "infohash_v1": "11984415d50696dff491afe11f329b92b13228f7",
        "infohash_v2": "",
        "last_activity": 1777955654,
        "magnet_uri": "magnet:?xt=urn:btih:11984415d50696dff491afe11f329b92b13228f7&dn=Stranger.Things.Tales.from.85.S01.MULTi.VF2.1080p.WEB.H265-SUPPLY&tr=https%3A%2F%2Fc411.org%2Fannounce%2FREDACTED_C411_PASSKEY",
        "max_inactive_seeding_time": -1,
        "max_ratio": -1,
        "max_seeding_time": -1,
        "name": "Stranger.Things.Tales.from.85.S01.MULTi.VF2.1080p.WEB.H265-SUPPLY",
        "num_complete": 594,
        "num_incomplete": 7,
        "num_leechs": 0,
        "num_seeds": 0,
        "popularity": 0.21577498515709312,
        "priority": 0,
        "private": true,
        "progress": 1,
        "ratio": 0.007888609250845233,
        "ratio_limit": -2,
        "reannounce": 254,
        "root_path": "/Volumes/IznoServer SSD/torrents/complete/Stranger.Things.Tales.from.85.S01.MULTi.VF2.1080p.WEB.H265-SUPPLY",
        "save_path": "/Volumes/IznoServer SSD/torrents/complete",
        "seeding_time": 95987,
        "seeding_time_limit": -2,
        "seen_complete": 1778009100,
        "seq_dl": false,
        "size": 13728288749,
        "state": "stalledUP",
        "super_seeding": false,
        "tags": "",
        "time_active": 96142,
        "total_size": 13728288749,
        "tracker": "https://c411.org/announce/REDACTED_C411_PASSKEY",
        "trackers_count": 1,
        "up_limit": 0,
        "uploaded": 108508790,
        "uploaded_session": 0,
        "upspeed": 0
    },
    {
        "added_on": 1777812766,
        "amount_left": 0,
        "auto_tmm": true,
        "availability": -1,
        "category": "",
        "comment": "",
        "completed": 4385044431,
        "completion_on": 1777812828,
        "content_path": "/Volumes/IznoServer SSD/torrents/complete/LOL.Qui.Rit.Sort.S06.FRENCH.AD.1080p.WEBRip.AMZ.x265.10bits.EAC3.5.1-Amen",
        "dl_limit": 0,
        "dlspeed": 0,
        "download_path": "/Volumes/IznoServer SSD/torrents/incomplete",
        "downloaded": 4390350483,
        "downloaded_session": 0,
        "eta": 8640000,
        "f_l_piece_prio": false,
        "force_start": false,
        "has_metadata": true,
        "hash": "86156bd4707f074007caf5b7b54216e5ab6f87d2",
        "inactive_seeding_time_limit": -2,
        "infohash_v1": "86156bd4707f074007caf5b7b54216e5ab6f87d2",
        "infohash_v2": "",
        "last_activity": 1777979318,
        "magnet_uri": "magnet:?xt=urn:btih:86156bd4707f074007caf5b7b54216e5ab6f87d2&dn=LOL.Qui.Rit.Sort.S06.FRENCH.AD.1080p.WEBRip.AMZ.x265.10bits.EAC3.5.1-Amen&tr=https%3A%2F%2Fc411.org%2Fannounce%2FREDACTED_C411_PASSKEY",
        "max_inactive_seeding_time": -1,
        "max_ratio": -1,
        "max_seeding_time": -1,
        "name": "LOL.Qui.Rit.Sort.S06.FRENCH.AD.1080p.WEBRip.AMZ.x265.10bits.EAC3.5.1-Amen",
        "num_complete": 284,
        "num_incomplete": 13,
        "num_leechs": 0,
        "num_seeds": 0,
        "popularity": 5.624210265413565,
        "priority": 0,
        "private": true,
        "progress": 1,
        "ratio": 0.4100530843655654,
        "ratio_limit": -2,
        "reannounce": 254,
        "root_path": "/Volumes/IznoServer SSD/torrents/complete/LOL.Qui.Rit.Sort.S06.FRENCH.AD.1080p.WEBRip.AMZ.x265.10bits.EAC3.5.1-Amen",
        "save_path": "/Volumes/IznoServer SSD/torrents/complete",
        "seeding_time": 191668,
        "seeding_time_limit": -2,
        "seen_complete": 1778009109,
        "seq_dl": false,
        "size": 4385044431,
        "state": "stalledUP",
        "super_seeding": false,
        "tags": "",
        "time_active": 191731,
        "total_size": 4385044431,
        "tracker": "https://c411.org/announce/REDACTED_C411_PASSKEY",
        "trackers_count": 1,
        "up_limit": 0,
        "uploaded": 1800276757,
        "uploaded_session": 0,
        "upspeed": 0
    }
]
